georeader/__init__.py
georeader/reader.py
georeader/tester.py
georeader/handlers/__init__.py
georeader/handlers/base_handler.py
georeader/handlers/csv_handler.py
georeader/handlers/esri_rest_handler.py
georeader/handlers/general_handler.py
georeader/handlers/geopandas_dataframe_handler.py
georeader/handlers/gml_handler.py
georeader/handlers/gpkg_handler.py
georeader/handlers/json_handler.py
georeader/handlers/kml_handler.py
georeader/handlers/layer_handler.py
georeader/handlers/open_file_gdb_handler.py
georeader/handlers/postgresql_handler.py
georeader/handlers/shape_file_handler.py
georeader/handlers/wfs_handler.py
georeader/handlers/zipped_handler.py
georeader/handlers/helpers/GDAL_type_list.py
georeader/handlers/helpers/__init__.py
georeader/handlers/helpers/directory_helper.py
georeader/handlers/helpers/handler_decorators.py
georeader/handlers/helpers/handlers.py
georeader/handlers/helpers/handler_getters/__init__.py
georeader/handlers/helpers/handler_getters/db_handlers.py
georeader/handlers/helpers/handler_getters/file_handlers.py
georeader/handlers/helpers/handler_getters/service_handlers.py
georeader/handlers/helpers/handler_getters/zip_handlers.py
georeader/logic/__init__.py
georeader/logic/converters.py
georeader/logic/error_exceptions.py
georeader/logic/main_helpers.py
georeader/logic/ogr_helpers.py
georeader/logic/thread_helper.py
georeader/logic/ogr/__init__.py
georeader/logic/ogr/data_source.py
georeader/logic/ogr/layer.py
georeader/tests/__init__.py
georeader/tests/test_helpers.py
georeader/tests/handler_tests/__init__.py
georeader/tests/handler_tests/reader_csv_test.py
georeader/tests/handler_tests/reader_esri_rest_test.py
georeader/tests/handler_tests/reader_geopackage_test.py
georeader/tests/handler_tests/reader_gml_reader_test.py
georeader/tests/handler_tests/reader_json_test.py
georeader/tests/handler_tests/reader_kml_test.py
georeader/tests/handler_tests/reader_shape_file_test.py
georeader/tests/handler_tests/reader_shape_file_test_2.py
georeader-0.1.13.dist-info/LICENSE
georeader-0.1.13.dist-info/METADATA
georeader-0.1.13.dist-info/WHEEL
georeader-0.1.13.dist-info/top_level.txt
georeader-0.1.13.dist-info/RECORD
