Metadata-Version: 2.1
Name: georeader
Version: 0.1.13
Summary: Module for reading spatial data files and services
Home-page: https://github.com/Improvement-Service/georeader
Author: Nathan Atkinson
Author-email: N00dlnate@gmail.com
License: MIT
Keywords: geo development
Platform: UNKNOWN
Classifier: Development Status :: 3 - Alpha
Classifier: Intended Audience :: Developers
Classifier: License :: OSI Approved :: MIT License
Classifier: Programming Language :: Python :: 3.8
Requires-Python: >=3.7
License-File: LICENSE
Requires-Dist: wheel
Requires-Dist: requests
Requires-Dist: pandas (>=1.4.3)
Requires-Dist: shapely (<2,>=1.7)
Requires-Dist: fiona (>=1.8.2)
Requires-Dist: geopandas (>=0.10.2)
Requires-Dist: py7zr (>=0.20.6)
Requires-Dist: validators (>=0.18.2)
Requires-Dist: owslib (==0.27.2)
Requires-Dist: pyshp (>=2.2.0)
Requires-Dist: GDAL (>=3.4.3)
Provides-Extra: dev
Provides-Extra: test
